.hgignore
ABOUT.txt
CHANGES.txt
COPYRIGHT.txt
LICENSE.txt
README.txt
bootstrap.py
buildout.cfg
setup.py
.bugs/bugs
tl/__init__.py
tl.pkg.egg-info/PKG-INFO
tl.pkg.egg-info/SOURCES.txt
tl.pkg.egg-info/dependency_links.txt
tl.pkg.egg-info/entry_points.txt
tl.pkg.egg-info/namespace_packages.txt
tl.pkg.egg-info/not-zip-safe
tl.pkg.egg-info/requires.txt
tl.pkg.egg-info/top_level.txt
tl/pkg/__init__.py
tl/pkg/doc.py
tl/pkg/sphinxconf.py
tl/pkg/template.py
tl/pkg/tests/__init__.py
tl/pkg/tests/test_doc.py
tl/pkg/tests/test_tl_pkg.py
tl/pkg/themes/tl-pkg/project-links.html
tl/pkg/themes/tl-pkg/theme.conf
tl/pkg/themes/tl-pkg/static/custom.css
tl/pkg/themes/tl-pkg/templates/autosummary/module.rst
tl/pkg/tl_pkg_template/ABOUT.txt_tmpl
tl/pkg/tl_pkg_template/CHANGES.txt_tmpl
tl/pkg/tl_pkg_template/COPYRIGHT.txt_tmpl
tl/pkg/tl_pkg_template/LICENSE.txt
tl/pkg/tl_pkg_template/README.txt_tmpl
tl/pkg/tl_pkg_template/bootstrap.py
tl/pkg/tl_pkg_template/buildout.cfg_tmpl
tl/pkg/tl_pkg_template/hgignore_tmpl
tl/pkg/tl_pkg_template/hgrc_tmpl
tl/pkg/tl_pkg_template/local.cfg_tmpl
tl/pkg/tl_pkg_template/setup.py_tmpl
tl/pkg/tl_pkg_template/+namespace+/__init__.py
tl/pkg/tl_pkg_template/+namespace+/+package+/__init__.py
tl/pkg/tl_pkg_template/+namespace+/+package+/tests/__init__.py
tl/pkg/tl_pkg_template/+namespace+/+package+/tests/test_doctests.py_tmpl
tl/pkg/tl_pkg_template/doc/about.txt_tmpl
tl/pkg/tl_pkg_template/doc/api.txt_tmpl
tl/pkg/tl_pkg_template/doc/changes.txt_tmpl
tl/pkg/tl_pkg_template/doc/conf.py_tmpl
tl/pkg/tl_pkg_template/doc/index.txt_tmpl
tl/pkg/tl_pkg_template/doc/narrative.txt_tmpl
tl/pkg/tl_pkg_template/doc/overview.txt_tmpl
tl/pkg/tl_pkg_template/doc/requirements.pip
tl/pkg/tl_pkg_template/versions/versions.cfg_tmpl
tl/pkg/tl_pkg_template/versions/ztk-versions-1.1.4.cfg
versions/versions.cfg
versions/ztk-versions-1.1.4.cfg