Metadata-Version: 1.0
Name: tl.pkg
Version: 0.1
Summary: A paste.script template for a namespaced Python package and a Sphinx theme.
Home-page: https://bitbucket.org/tlotze/tl.pkg/
Author: Thomas Lotze
Author-email: thomas@thomas-lotze.de
License: ZPL 2.1
Keywords: paste.script paster create template python package sphinx docs theme development buildout
Platform: UNKNOWN
Classifier: Environment :: Plugins
Classifier: Framework :: Paste
Classifier: Intended Audience :: Developers
Classifier: License :: OSI Approved :: Zope Public License
Classifier: Programming Language :: Python
Classifier: Programming Language :: Python :: 2
Classifier: Programming Language :: Python :: 2.6
Classifier: Programming Language :: Python :: 2.7
Classifier: Programming Language :: Python :: 2 :: Only
